{
  "description": "项目配置文件",
  "packOptions": {
    "ignore": [],
    "include": []
  },
  "miniprogramRoot": "",
  "compileType": "miniprogram",
  "projectname": "走心拜年",
  "setting": {
    "useCompilerPlugins": [
      "sass"
    ],
    "babelSetting": {
      "ignore": [],
      "disablePlugins": [],
      "outputPath": ""
    },
    "es6": true,
    "enhance": true,
    "postcss": true,
    "minified": true,
    "uglifyFileName": true,
    "lazyCodeLoading": "requiredComponents"
  },
  "simulatorType": "wechat",
  "simulatorPluginLibVersion": {},
  "condition": {},
  "srcMiniprogramRoot": "miniprogram/",
  "appid": "wxaeb48615b48992d0",
  "libVersion": "3.0.0",
  "editorSetting": {
    "tabIndent": "insertSpaces",
    "tabSize": 2
  }
}